ghee/__init__.py
ghee/ghee.py
ghee-0.0.3.dist-info/LICENSE
ghee-0.0.3.dist-info/METADATA
ghee-0.0.3.dist-info/WHEEL
ghee-0.0.3.dist-info/entry_points.txt
ghee-0.0.3.dist-info/top_level.txt
ghee-0.0.3.dist-info/RECORD
