Metadata-Version: 2.1
Name: ghee
Version: 0.0.3
Summary: Tiny tool for sending messages to google chat via http webhook
Home-page: https://github.com/chomik/ghee
Author: Michał Chałupczak
Author-email: michal@chalupczak.info
License: UNKNOWN
Platform: UNKNOWN
Classifier: Programming Language :: Python :: 3
Classifier: License :: OSI Approved :: MIT License
Classifier: Operating System :: OS Independent
Requires-Python: >=3.6
